MANIFEST.in
README
setup.py
bin/fpr
bin/fpr-irc
bin/fpr-release
bin/fpr-run
bin/fpr-upload
commonplugs/8b.py
commonplugs/__init__.py
commonplugs/ask.py
commonplugs/gcalc.py
commonplugs/hubbub.py
commonplugs/ipcalc.py
commonplugs/relay.py
commonplugs/remote.py
commonplugs/tinyurl.py
commonplugs/todo.py
commonplugs/watcher.py
commonplugs/wikipedia.py
config/README
config/__init__.py
config/app.yaml.example
config/credentials.py.example
config/mainconfig.example
feedprovider.egg-info/PKG-INFO
feedprovider.egg-info/SOURCES.txt
feedprovider.egg-info/dependency_links.txt
feedprovider.egg-info/not-zip-safe
feedprovider.egg-info/requires.txt
feedprovider.egg-info/top_level.txt
gaeupload/__init__.py
gaeupload/app.yaml.example
gaeupload/handler_gadgetexec.py
gaeupload/handler_hubbub.py
gaeupload/handler_remote.py
gaeupload/handler_task.py
gaeupload/handler_wave.py
gaeupload/handler_web.py
gaeupload/handler_xmpp.py
gaeupload/assets/basic.css
gaeupload/assets/default.css
gaeupload/assets/doctools.js
gaeupload/assets/favicon.ico
gaeupload/assets/favicon.png
gaeupload/assets/feedprovider_screenshot.png
gaeupload/assets/file.png
gaeupload/assets/jquery.js
gaeupload/assets/minus.png
gaeupload/assets/plus.png
gaeupload/assets/profile.json
gaeupload/assets/pygments.css
gaeupload/assets/screenshot.png
gaeupload/assets/searchtools.js
gaeupload/gadgets/cmnd.xml
gaeupload/gadgets/exec.xml
gaeupload/gadgets/feeder.xml
gaeupload/gadgets/feedform.xml
gaeupload/gadgets/feedmanifest.xml
gaeupload/gadgets/feedwave.xml
gaeupload/gadgets/gadget.xml
gaeupload/gadgets/iframe.xml
gaeupload/gadgets/loadiframe.xml
gaeupload/gadgets/manifest.xml
gaeupload/gadgets/poll.xml
gaeupload/templates/start.html
gaeupload/waveapi/__init__.py
gaeupload/waveapi/appengine_robot_runner.py
gaeupload/waveapi/blip.py
gaeupload/waveapi/blip_test.py
gaeupload/waveapi/commandline_robot_runner.py
gaeupload/waveapi/commandline_robot_runner_test.py
gaeupload/waveapi/element.py
gaeupload/waveapi/element_test.py
gaeupload/waveapi/errors.py
gaeupload/waveapi/events.py
gaeupload/waveapi/module_test_runner.py
gaeupload/waveapi/ops.py
gaeupload/waveapi/ops_test.py
gaeupload/waveapi/robot.py
gaeupload/waveapi/robot_test.py
