Metadata-Version: 1.0
Name: feedprovider
Version: 0.2.1
Summary: The hubbub bot of the future!
Home-page: http://feedprovider.googlecode.com/
Author: Bart Thate
Author-email: bthate@gmail.com
License: MIT
Download-URL: http://code.google.com/p/feedprovider/downloads
Platform: UNKNOWN
Classifier: Development Status :: 4 - Beta
Classifier: Environment :: Console
Classifier: Environment :: Other Environment
Classifier: Intended Audience :: Developers
Classifier: License :: OSI Approved :: MIT License
Classifier: Operating System :: Unix
Classifier: Operating System :: Other OS
Classifier: Programming Language :: Python
Classifier: Topic :: Communications :: Chat
Classifier: Topic :: Software Development :: Libraries :: Python Modules
